iotcore-0.3.0.dist-info/METADATA
iotcore-0.3.0.dist-info/WHEEL
iotcore-0.3.0.dist-info/license_files/LICENSE.txt
iotcore/mqtt.py
iotcore/_iotcore.pyi
iotcore/djangoiot/views.py
iotcore/djangoiot/models.py
iotcore/djangoiot/migrations/__init__.py
iotcore/djangoiot/__init__.py
iotcore/djangoiot/apps.py
iotcore/djangoiot/tests.py
iotcore/djangoiot/admin.py
iotcore/__init__.py
iotcore/py.typed
iotcore/fastapi/life_span.py
iotcore/fastapi/__init__.py
iotcore/request.py
iotcore/_iotcore.cpython-39-x86_64-linux-gnu.so
iotcore-0.3.0.dist-info/RECORD
